blocks/__init__.py
blocks/antisymmetrization.py
blocks/discretization.py
blocks/embed.py
blocks/energy_initialization.py
blocks/hamiltonian.py
blocks/qft.py
blocks/time_evolution.py
blocks/wave_function.py
slater/__init__.py
slater/aregister.py
slater/bregister.py
slater/sigma.py
top/firstq.py
utils/amplitudes.py
utils/setdistribution.py
utils/statevector.py
crsq_main-0.0.1.dist-info/METADATA
crsq_main-0.0.1.dist-info/WHEEL
crsq_main-0.0.1.dist-info/licenses/LICENSE
crsq_main-0.0.1.dist-info/RECORD
